__init__.py
fmri/__init__.py
fmri/b_spline_bspline.py
fmri/b_spline_skfda.py
fmri/evaluate_lambda.py
fmri/fmri.py
fmri/gcv_solver.py
fmri/pc_similarity.py
fmri/peaks_similarity.py
fmri/preprocess.py
fmri/represent_pc.py
fmri/similarity.py
fmri/utils.py
fmri/alternative_code/__init__.py
fmri/alternative_code/b-spline.py
fmri/alternative_code/evaluate_lambda.py
fmri/alternative_code/main.py
fmri/alternative_code/main_old.py
fmri/alternative_code/pca.py
fmri/analysis_exp_visual_audio/__init__.py
fmri/analysis_exp_visual_audio/classify_pcs.py
fmri/analysis_exp_visual_audio/heatmap_design.py
fmri/analysis_exp_visual_audio/settings.py
fmri/analysis_exp_visual_audio/old-code/Amplitude_Heatmaps.png
fmri/analysis_exp_visual_audio/old-code/CONTRAST_Analysis_V_minus_A.png
fmri/analysis_exp_visual_audio/old-code/Final_Analysis_Amplitude_Scrollable.png
fmri/analysis_exp_visual_audio/old-code/GLM_vs_Simple_Correlation_Heatmaps.png
fmri/analysis_exp_visual_audio/old-code/classify_pcs_back.py
fmri/analysis_exp_visual_audio/old-code/classify_pcs_v0.py
fmri/analysis_exp_visual_audio/old-code/classify_pcs_v1.py
fmri/analysis_exp_visual_audio/old-code/classify_pcs_v2.py
fmri/analysis_exp_visual_audio/old-code/classify_pcs_v3.py
fmri/analysis_exp_visual_audio/old-code/classify_pcs_v4.py
fmri/analysis_exp_visual_audio/old-code/classify_pcs_v5.py
fmri/analysis_exp_visual_audio/old-code/classify_pcs_work.py
fmri/analysis_exp_visual_audio/old-code/diag.py
fmri/analysis_exp_visual_audio/output/CONTRAST_Analysis.png
fmri/analysis_exp_visual_audio/output/detailed_region_analysis.txt
fmri/analysis_exp_visual_audio/output/full_correlation_results.csv
fmri/analysis_exp_visual_audio/output/spatial_correlation_summary.txt
fmri/analysis_exp_visual_audio/output/temporal_PC_0.png
fmri/analysis_exp_visual_audio/output/temporal_PC_1.png
fmri/analysis_exp_visual_audio/output/temporal_PC_2.png
fmri/analysis_exp_visual_audio/output/temporal_PC_3.png
fmri/analysis_exp_visual_audio/output/temporal_PC_4.png
neuro_fpca_fmri-0.0.5.dist-info/licenses/AUTHORS.rst
neuro_fpca_fmri-0.0.5.dist-info/licenses/LICENSE
neuro_fpca_fmri-0.0.5.dist-info/METADATA
neuro_fpca_fmri-0.0.5.dist-info/WHEEL
neuro_fpca_fmri-0.0.5.dist-info/entry_points.txt
neuro_fpca_fmri-0.0.5.dist-info/top_level.txt
neuro_fpca_fmri-0.0.5.dist-info/RECORD
