Metadata-Version: 2.4
Name: Neuro-fPCA-fMRI
Version: 0.0.5
Summary: Functional PCA on fMRI data to extract dominant temporal components.
Author-email: Refael Kohen <refael.kohen@gmail.com>
Maintainer-email: Refael Kohen <refael.kohen@gmail.com>
License: GNU General Public License v3
Project-URL: bugs, https://github.com/yanivassf-lab/fMRI/issues
Project-URL: changelog, https://github.com/yanivassf-lab/fMRI/blob/master/changelog.md
Project-URL: homepage, https://github.com/yanivassf-lab/fMRI
License-File: LICENSE
License-File: AUTHORS.rst
Requires-Dist: pip
Requires-Dist: bump2version==0.5.11
Requires-Dist: wheel==0.33.6
Requires-Dist: watchdog==6.0.0
Requires-Dist: tox==3.14.0
Requires-Dist: coverage==4.5.4
Requires-Dist: Sphinx==7.2.6
Requires-Dist: twine==5.0.0
Requires-Dist: ruff==0.3.5
Requires-Dist: pytest==6.2.4
Requires-Dist: matplotlib==3.10.1
Requires-Dist: nibabel==5.3.2
Requires-Dist: numpy==2.2.3
Requires-Dist: scipy==1.15.2
Requires-Dist: scikit-fda==0.10.1
Requires-Dist: dtaidistance==2.3.13
Provides-Extra: dev
Requires-Dist: coverage; extra == "dev"
Requires-Dist: mypy; extra == "dev"
Requires-Dist: pytest; extra == "dev"
Requires-Dist: ruff; extra == "dev"
Dynamic: license-file
